PyInvest-1.0.1.data/data/pyinvestconf/pyinvest.json
PyInvest-1.0.1.data/scripts/tda_allocations
PyInvest-1.0.1.data/scripts/tdaorders
PyInvest-1.0.1.data/scripts/tdapositions
pyinvest/__init__.py
pyinvest/accounts.py
pyinvest/auth.py
pyinvest/config.py
PyInvest-1.0.1.dist-info/LICENSE
PyInvest-1.0.1.dist-info/METADATA
PyInvest-1.0.1.dist-info/WHEEL
PyInvest-1.0.1.dist-info/top_level.txt
PyInvest-1.0.1.dist-info/RECORD
