Metadata-Version: 2.1
Name: PyInvest
Version: 1.0.1
Summary: A Python wrapper for the TD Ameritrade REST API
Home-page: UNKNOWN
Author: Jeff Moorhead
Author-email: Jeff.moorhead1@gmail.com
License: UNKNOWN
Platform: UNKNOWN
Requires-Dist: requests
Requires-Dist: selenium
